pdfdocx/__init__.py
pdfdocx/readfile.py
pdfdocx-1.7.dist-info/LICENSE
pdfdocx-1.7.dist-info/METADATA
pdfdocx-1.7.dist-info/WHEEL
pdfdocx-1.7.dist-info/top_level.txt
pdfdocx-1.7.dist-info/RECORD
