Metadata-Version: 2.1
Name: pdfdocx
Version: 1.7
Summary: 读取pdf、docx文件，返回文件内的文本数据。
Home-page: https://github.com/hidadeng/pdfdocx
Author: 大邓
Author-email: thunderhit@qq.com
License: MIT
Keywords: pdf extraction,docx extraction,text mining
Requires-Python: >=3.5
License-File: LICENSE
Requires-Dist: PyMuPDF
Requires-Dist: python-docx
